rwkvstic/__init__.py
rwkvstic/__main__.py
rwkvstic/bench.py
rwkvstic/load.py
rwkvstic/preJax.py
rwkvstic/preQuantize.py
rwkvstic/rwkvMaster.py
rwkvstic/server.py
rwkvstic/agnostic/__init__.py
rwkvstic/agnostic/agnosticRwkv.py
rwkvstic/agnostic/rnn.py
rwkvstic/agnostic/backends/__init__.py
rwkvstic/agnostic/backends/base.py
rwkvstic/agnostic/backends/coreml.py
rwkvstic/agnostic/backends/jax.py
rwkvstic/agnostic/backends/onnx.py
rwkvstic/agnostic/backends/opt.py
rwkvstic/agnostic/backends/tensorflow.py
rwkvstic/agnostic/backends/torch.py
rwkvstic/agnostic/backends/cuda/operators.cu
rwkvstic/agnostic/backends/cuda/operators32.cu
rwkvstic/agnostic/backends/cuda/wrapper.cpp
rwkvstic/agnostic/backends/hip/operators.hip
rwkvstic/agnostic/backends/hip/wrapper.cpp
rwkvstic/agnostic/backends/modules/base.py
rwkvstic/agnostic/backends/modules/block.py
rwkvstic/agnostic/backends/modules/emb.py
rwkvstic/agnostic/backends/modules/layernorm.py
rwkvstic/agnostic/backends/modules/matmul.py
rwkvstic/agnostic/samplers/__init__.py
rwkvstic/agnostic/samplers/numpy.py
rwkvstic/agnostic/samplers/torch.py
rwkvstic/helpers/loadWeights.py
rwkvstic/interOpLoaders/__init__.py
rwkvstic/interOpLoaders/chatRWKV.py
rwkvstic/interOpLoaders/onnx.py
rwkvstic/interOpLoaders/preJax.py
rwkvstic/interOpLoaders/prequantized.py
rwkvstic/interOpLoaders/rwkvRs.py
rwkvstic/interOpLoaders/tflite.py
rwkvstic/interOpLoaders/torchscript.py
rwkvstic/tokenizer/20B_tokenizer.json
rwkvstic/tokenizer/__init__.py
rwkvstic/tools/getBestSetup.py
rwkvstic/tools/getBestSetupCpu.py
rwkvstic/training/model.py
rwkvstic/training/data/t8.shakespeare.txt
rwkvstic/training/modules/block.py
rwkvstic/training/modules/wkv.py
rwkvstic-2.1.2.dist-info/METADATA
rwkvstic-2.1.2.dist-info/WHEEL
rwkvstic-2.1.2.dist-info/licenses/LICENSE
rwkvstic-2.1.2.dist-info/RECORD
