Metadata-Version: 2.1
Name: rwkvstic
Version: 2.1.2
Summary: A package for loading rwkv on a larger range of devices
Project-URL: Homepage, https://github.com/harrisonvanderbyl/rwkvstic
Project-URL: Bug Tracker, https://github.com/harrisonvanderbyl/rwkvstic/issues
Author-email: Harrison Vanderbyl <harrison.vanderbyl@gmail.com>
License-File: LICENSE
Classifier: License :: OSI Approved :: MIT License
Classifier: Operating System :: OS Independent
Classifier: Programming Language :: Python :: 3
Requires-Python: >=3.7
Requires-Dist: ninja
Requires-Dist: numpy
Requires-Dist: rwkv
Requires-Dist: tokenizers>=0.13.2
Requires-Dist: tqdm
